mbed/__init__.py
mbed/__main__.py
mbed/mbed.py
mbed/mbed_terminal.py
mbed_cli-1.10.4.dist-info/LICENSE
mbed_cli-1.10.4.dist-info/METADATA
mbed_cli-1.10.4.dist-info/WHEEL
mbed_cli-1.10.4.dist-info/entry_points.txt
mbed_cli-1.10.4.dist-info/top_level.txt
mbed_cli-1.10.4.dist-info/RECORD
