Metadata-Version: 2.1
Name: mbed-cli
Version: 1.10.4
Summary: Command line tool for interacting with Mbed OS projects
Home-page: http://github.com/ARMmbed/mbed-cli
Author: Arm mbed
Author-email: support@mbed.org
License: Apache 2.0
Keywords: Mbed OS CLI
Platform: UNKNOWN
Classifier: Development Status :: 5 - Production/Stable
Classifier: Intended Audience :: Developers
Classifier: License :: OSI Approved :: Apache Software License
Classifier: Programming Language :: Python :: 2
Classifier: Programming Language :: Python :: 2.7
Classifier: Programming Language :: Python :: 3
Classifier: Programming Language :: Python :: 3.5
Classifier: Programming Language :: Python :: 3.6
Classifier: Programming Language :: Python :: 3.7
Classifier: Programming Language :: Python
Classifier: Topic :: Software Development :: Build Tools
Classifier: Topic :: Software Development :: Embedded Systems
Requires-Python: >=2.7.10, !=3.0.*, !=3.1.*, !=3.2.*, !=3.3.*, !=3.4.*, <4
Requires-Dist: pyserial (<4.0,>=3.0)
Requires-Dist: mbed-os-tools (<0.1.0,>=0.0.9)
